sim/global_config.vh
`define GLOBAL_BUSADDRWID 64
`define GLOBAL_BUSDATAWID 64
`define GPU_CACHE_DATAWID 64
`define GPU_DDATA_WIDTH 64
`define GPU_DADDR_WIDTH 64
`define GPU_IADDR_WIDTH 64

`define GPU_LANE_WIDTH 16
`define GPU_LANE_NUM 8

`define GPU_VDATA_WIDTH `GPU_LANE_WIDTH*`GPU_LANE_NUM
`define DUMP_VCD

RTL/CPU/EX/bshifter16.v
/*
Type: 00/01=Left Shift
10=Right Shift, 0 Filled
11=Right Shift,with symbol extent
*/
module bshifter16(
    input [15:0]datain,
    input [1:0]typ,
    input [3:0]shiftnum,
    output [15:0]dataout
);
wire [15:0]shift0;
wire [15:0]shift1;
wire [15:0]shift2;
wire [15:0]shift3;
assign shift0=(
    (shiftnum[0])?
    (typ[1]?{{1{datain[15]&typ[0]}},datain[15:1]}:{datain[14:0],1'b0}):
    (datain));
assign shift1=(
    (shiftnum[1])?
    (typ[1]?{{2{datain[15]&typ[0]}},shift0[15:2]}:{shift0[13:0],2'b0}):
    (shift0)
    );
assign shift2=(
    (shiftnum[2])?
    (typ[1]?{{4{datain[15]&typ[0]}},shift1[15:4]}:{shift1[11:0],4'b0}):
    (shift1)
    );
assign shift3=(
    (shiftnum[3])?
    (typ[1]?{{8{datain[15]&typ[0]}},shift2[15:8]}:{shift2[7:0],8'b0}):
    (shift2)
    );
assign dataout=shift3;




endmodule

RTL/CPU/EX/VPU/FALU16.v
/****************************************
This is 16bit FPU, can only do half add/sub/mul 
for HGA101 project

****************************************/
`include "global_config.vh"
module FALU16
(
    input enable,
    input [15:0]op1,
    input [15:0]op2,
    input vec_en,//enable VECTOR (replace op2 with fullin)
    input addsel,//Add/subtract control 0=add,1=subtract
    input subsel,//add/sub select
    input mulsel, //multiply select
    input itfsel, //integer to float
    input ftisel, //float to integer
    input maxsel,
    input minsel,
    input [31:0]fullin,//Full range float in 
    input ftlsel,
    output [31:0]fullout,//float out to float reg
    output [15:0]opout,
    output gt,
    output eq
);

wire sign1,sign2;
wire [4:0]exp1;
wire [4:0]exp2;
wire exp_sgn1,exp_sgn2;
//wire [4:0]exp_diff;

wire [9:0]val1;
wire [9:0]val2;
wire inf1,inf2,nan1,nan2;
wire zero1,zero2;
assign sign1=(ftlsel)?ftlout[15]:op1[15];
assign sign2=(vec_en)?ftlout[15]:op2[15];//(fullin-float to half->ftlout->go to calc)
assign exp1=(ftlsel)?ftlout[14:10]:op1[14:10];
assign exp2=(vec_en)?ftlout[14:10]:op2[14:10];
assign val1=(ftlsel)?ftlout[9:0]:op1[9:0];
assign val2=(vec_en)?ftlout[9:0]:op2[9:0];
//op status generation
assign nan1=(val1!=0&(exp1==5'h1f));//NaN Gen
assign nan2=(val2!=0&(exp2==5'h1f));
assign inf1=(val1==0&(exp1==5'h1f));//Inf Gen
assign inf2=(val2==0&(exp2==5'h1f));
assign zero1=(exp1==0&val1==0);
assign zero2=(exp2==0&val2==0);
//FCMP
wire [1:0]exp_cmp; //00=expA>expB,01=expA<expB,10=expA=expB
wire [5:0]exp_diff;
wire [5:0]exp_dif1,exp_dif2;
wire [10:0]base_smaller;
wire [10:0]base_larger;
wire much_larger,diff_sym;
assign diff_sym=sign1^sign2;
assign exp_diff=exp_dif1-exp_dif2;
assign much_larger=(exp_diff>5'd10);
//generate difference of exponential word
assign exp_cmp=(exp1==exp2)?2'b10:
        (exp1>exp2)?2'b00:2'b01;
assign exp_dif1=(exp_cmp[0])?exp1:exp2;
assign exp_dif2=(!exp_cmp[0])?exp1:exp2;
assign base_larger=(exp_cmp[0])?{1'b1,val1}:{1'b1,val2};
assign base_smaller=(!exp_cmp[0])?{1'b1,val1}:{1'b1,val2};
assign eq=(op1==op2);
assign gt=(diff_sym)?((sign1==0)?1'b1:1'b0)://Condition:Different symbol
        ((sign1==0)?                           //condition:both positive
                ((exp_cmp[1])?(!exp_cmp[0]):(val1>val2))://if so,if exp1!=exp2,larger exp,eles larger val
                ((exp_cmp[1])?(exp_cmp[0]):(val1<val2)));//both neg case
//FASUB
wire [15:0]acalc;
wire [9:0]aval;
wire [10:0]aout;
wire [10:0]aligned_out;
bshifter16 fshifter1
(
    .datain(base_smaller),
    .shiftnum(exp_diff),
    .typ(2'b10),
    .dataout(aligned_out)
);

assign acalc=(much_larger)?
            (exp_cmp[0]?op1:op2)://in case one is much larger than another, just output the larger
            ({sign1,exp_dif1,aval[9:0]});
assign aval=((sign1^sign2)^subsel)?((aout[10])?aout:((~aout)+1)):aout;//always give out abs
assign aout=(base_larger+(subsel)?(~aligned_out)+1:aligned_out);
//assign ASout=(enable)?acalc:op1;
//FMUL
wire [19:0]valmul;
wire [5:0]expmul;
wire [15:0]mcalc;
assign valmul=val1*val2;
assign expmul=exp1+exp2-6'd15;
assign mcalc=(enable)?{sign1^sign2,expmul[4:0],valmul[19:10]}:op1;


//integer to float
wire [15:0]itfcalc;
reg [3:0]exp_get;
wire [4:0]itf_exp;
wire [15:0]itf_shift;
assign itf_exp=(op1!=0)?exp_get+4'hf:4'h0;
always@(op1[14:0])
    casex(op1[14:0]) 
        15'b1xx_xxxx_xxxx_xxxx:exp_get=4'hf;
        15'b01x_xxxx_xxxx_xxxx:exp_get=4'he;
        15'b001_xxxx_xxxx_xxxx:exp_get=4'hd;
        15'b000_1xxx_xxxx_xxxx:exp_get=4'hc;
        15'b000_01xx_xxxx_xxxx:exp_get=4'hb;
        15'b000_001x_xxxx_xxxx:exp_get=4'ha;
        15'b000_0001_xxxx_xxxx:exp_get=4'h9;
        15'b000_0000_1xxx_xxxx:exp_get=4'h8;
        15'b000_0000_01xx_xxxx:exp_get=4'h7;
        15'b000_0000_001x_xxxx:exp_get=4'h6;
        15'b000_0000_0001_xxxx:exp_get=4'h5;
        15'b000_0000_0000_1xxx:exp_get=4'h4;
        15'b000_0000_0000_01xx:exp_get=4'h3;
        15'b000_0000_0000_001x:exp_get=4'h2;
        15'b000_0000_0000_0001:exp_get=4'h1;
        15'b000_0000_0000_0000:exp_get=4'h0;
        default:exp_get=15'hx;
    endcase
bshifter16 itfshifter1
(
    .datain({op1[14:0],1'b0}),
    .shiftnum(exp_get+1),
    .typ(2'b00),//Left shift
    .dataout(itf_shift)
);

assign itfcalc={op1[15],itf_exp,itf_shift[15:5]};
//float to integer
wire [15:0]fticalc;
wire [15:0]ftival;
wire ftishiftdir,belowzero;
wire [15:0]ftishift;
wire [3:0]ftiexp;//exponential adjust
assign ftival=(sign1)?((~{6'h01,op1[9:0]})+1):{6'h01,op1[9:0]};//补码
assign ftishiftdir=(exp1>=5'h1a)?1'b0:1'b1;
assign ftiexp=(ftishiftdir)?(4'd10-exp1[4:0]):(exp1[4:0]-4'd10);
assign belowzero=(exp1<5'h10);

bshifter16 ftishifter1
(
    .datain(ftival),
    .shiftnum(ftiexp),
    .typ({ftishiftdir,1'b1}),//
    .dataout(ftishift)
);
assign fticalc=(belowzero)?16'b0:{op1[15],ftishift[14:0]};
wire [15:0]maxout,minout,ftlout;
wire [7:0] ftlexpgen,ltfexpgen;
assign maxout=(gt)?op1:op2;
assign minout=(gt)?op2:op1;
assign ftlexpgen=fullin[30:22]-8'd112;
assign ltfexpgen=exp1+8'd112;
assign ftlout={fullin[31],ftlexpgen[4:0],fullin[22:13]};
assign fullout={op1[15],ltfexpgen,val1,13'b0};
//OUTPUT STAGE    
assign opout=   (!enable 		? op1		: 16'b0)|//ds1直通,lane unchanged
			    ((addsel|subsel)? acalc 	: 16'b0)|//加
                (mulsel 		? mcalc 	: 16'b0)|
				(itfsel 		? itfcalc 	: 16'b0)|//short to half
                (ftisel 		? fticalc  	: 16'b0)|//half to short
                (maxsel 		? maxout 	: 16'b0)|//lane max
                (minsel 		? minout  	: 16'b0)|//lane max
                (ftlsel 		? ftlout  	: 16'b0); //float to half lane


endmodule

sim/RTL/fpu16_tb.v
`timescale 1ns/100ps
module fpu16_tb();
reg clk,asel,ssel,msel,dsel;
reg [15:0]op1[31:0];
reg [15:0]op2[31:0];
reg [6:0]opcnt;
wire [15:0]DOUT;
always #5 clk=~clk;
initial 
begin
    $dumpfile("./obj/fpu16_tb_dump.vcd"); // 指定用作dumpfile的文件
    $dumpvars; // dump all vars
    $readmemh("./obj/fop_a.hex",op1);
    $readmemh("./obj/fop_b.hex",op2);
    #0 clk=0;opcnt=0;{asel,ssel,msel,dsel}<=4'b1000;
end
always @(posedge clk)
begin
    opcnt<=opcnt+1;
    if(opcnt==7'h7f)$finish;
    case(opcnt[6:5])
        2'b00:{asel,ssel,msel,dsel}<=4'b1000;
        2'b01:{asel,ssel,msel,dsel}<=4'b0100;
        2'b10:{asel,ssel,msel,dsel}<=4'b0010;
        2'b11:{asel,ssel,msel,dsel}<=4'b0001;
    endcase
end

FALU16 DUT
(
    .enable(1'b1),
    .op1(op1[opcnt[4:0]]),
    .op2(op2[opcnt[4:0]]),
    .vec_en(1'b0),//enable VECTOR (replace op2 with fullin)
    .addsel(asel),//Add/subtract control 0=add,1=subtract
    .subsel(ssel),//add/sub select
    .mulsel(msel), //multiply select
    .itfsel(1'b0), //integer to float
    .ftisel(1'b0), //float to integer
    .maxsel(1'b0),
    .minsel(1'b0),
    .fullin(32'b0),//Full range float in 
    .ftlsel(1'b0),
    .fullout(),//float out to float reg
    .opout(DOUT),
    .gt(),
    .eq()
);

endmodule

sim/obj/fpu16_tb_dump.vcd
$date
	Wed Dec 16 17:46:41 2020
$end
$version
	Icarus Verilog
$end
$timescale
	100ps
$end
$scope module fpu16_tb $end
$var wire 16 ! DOUT [15:0] $end
$var reg 1 " asel $end
$var reg 1 # clk $end
$var reg 1 $ dsel $end
$var reg 1 % msel $end
$var reg 7 & opcnt [6:0] $end
$var reg 1 ' ssel $end
$scope module DUT $end
$var wire 1 " addsel $end
$var wire 1 ( diff_sym $end
$var wire 1 ) enable $end
$var wire 5 * exp1 [4:0] $end
$var wire 5 + exp2 [4:0] $end
$var wire 1 , ftisel $end
$var wire 1 - ftlsel $end
$var wire 32 . fullin [31:0] $end
$var wire 1 / inf1 $end
$var wire 1 0 inf2 $end
$var wire 1 1 itfsel $end
$var wire 1 2 maxsel $end
$var wire 16 3 mcalc [15:0] $end
$var wire 1 4 minsel $end
$var wire 1 % mulsel $end
$var wire 1 5 nan1 $end
$var wire 1 6 nan2 $end
$var wire 16 7 op1 [15:0] $end
$var wire 16 8 op2 [15:0] $end
$var wire 16 9 opout [15:0] $end
$var wire 1 : sign1 $end
$var wire 1 ; sign2 $end
$var wire 1 ' subsel $end
$var wire 10 < val1 [9:0] $end
$var wire 10 = val2 [9:0] $end
$var wire 1 > vec_en $end
$var wire 1 ? zero1 $end
$var wire 1 @ zero2 $end
$var wire 20 A valmul [19:0] $end
$var wire 1 B much_larger $end
$var wire 16 C minout [15:0] $end
$var wire 16 D maxout [15:0] $end
$var wire 8 E ltfexpgen [7:0] $end
$var wire 16 F itfcalc [15:0] $end
$var wire 16 G itf_shift [15:0] $end
$var wire 5 H itf_exp [4:0] $end
$var wire 1 I gt $end
$var wire 32 J fullout [31:0] $end
$var wire 16 K ftlout [15:0] $end
$var wire 8 L ftlexpgen [7:0] $end
$var wire 16 M ftival [15:0] $end
$var wire 1 N ftishiftdir $end
$var wire 16 O ftishift [15:0] $end
$var wire 4 P ftiexp [3:0] $end
$var wire 16 Q fticalc [15:0] $end
$var wire 6 R expmul [5:0] $end
$var wire 6 S exp_diff [5:0] $end
$var wire 6 T exp_dif2 [5:0] $end
$var wire 6 U exp_dif1 [5:0] $end
$var wire 2 V exp_cmp [1:0] $end
$var wire 1 W eq $end
$var wire 1 X belowzero $end
$var wire 11 Y base_smaller [10:0] $end
$var wire 11 Z base_larger [10:0] $end
$var wire 10 [ aval [9:0] $end
$var wire 11 \ aout [10:0] $end
$var wire 11 ] aligned_out [10:0] $end
$var wire 16 ^ acalc [15:0] $end
$var reg 4 _ exp_get [3:0] $end
$scope module fshifter1 $end
$var wire 16 ` datain [15:0] $end
$var wire 16 a dataout [15:0] $end
$var wire 4 b shiftnum [3:0] $end
$var wire 2 c typ [1:0] $end
$var wire 16 d shift3 [15:0] $end
$var wire 16 e shift2 [15:0] $end
$var wire 16 f shift1 [15:0] $end
$var wire 16 g shift0 [15:0] $end
$upscope $end
$scope module ftishifter1 $end
$var wire 16 h datain [15:0] $end
$var wire 16 i dataout [15:0] $end
$var wire 4 j shiftnum [3:0] $end
$var wire 2 k typ [1:0] $end
$var wire 16 l shift3 [15:0] $end
$var wire 16 m shift2 [15:0] $end
$var wire 16 n shift1 [15:0] $end
$var wire 16 o shift0 [15:0] $end
$upscope $end
$scope module itfshifter1 $end
$var wire 16 p datain [15:0] $end
$var wire 16 q dataout [15:0] $end
$var wire 4 r shiftnum [3:0] $end
$var wire 2 s typ [1:0] $end
$var wire 16 t shift3 [15:0] $end
$var wire 16 u shift2 [15:0] $end
$var wire 16 v shift1 [15:0] $end
$var wire 16 w shift0 [15:0] $end
$upscope $end
$upscope $end
$upscope $end
$enddefinitions $end
#0
$dumpvars
b1110100111100000 w
b1110100111100000 v
b1110100111100000 u
b1110100111100000 t
b0 s
b0 r
b1110100111100000 q
b1110100111100000 p
b1111011000100000 o
b1101100010000000 n
b1101100010000000 m
b1101100010000000 l
b1 k
b11 j
b1101100010000000 i
b1111101100010000 h
b1001111000 g
b10011110 f
b1001 e
b0 d
b10 c
b1111 b
b0 a
b10011110000 `
b1111 _
b1111000111000011 ^
b0 ]
b0 \
b0 [
b10111000011 Z
b10011110000 Y
0X
0W
b0 V
b11100 U
b11101 T
b111111 S
b101010 R
b1101100010000000 Q
b11 P
b1101100010000000 O
0N
b1111101100010000 M
b10010000 L
b100000000000000 K
b11000110100111100000000000000000 J
1I
b11110 H
b1110100111100000 G
b1111011101001111 F
b10001101 E
b1111010011110000 D
b1111000111000011 C
1B
b11010011011010000 A
0@
0?
0>
b111000011 =
b11110000 <
1;
1:
b1111000111000011 9
b1111000111000011 8
b1111010011110000 7
06
05
04
b10100001101001 3
02
01
00
0/
b0 .
0-
0,
b11100 +
b11101 *
1)
0(
0'
b0 &
0%
0$
0#
1"
b1111000111000011 !
$end
#50
b0 [
b111001011010100 !
b111001011010100 9
b1101101010000 O
b1101101010000 i
b1101101010000 l
b1101101010000 m
b1101101010000 n
b0 \
b1111011100101101 F
b0 ]
b11011010100 o
b1001100110 g
b1110010110101000 G
b1110010110101000 q
b1110010110101000 t
b10011001 f
b1001 e
b0 a
b0 d
b1110010110101000 u
b10 P
b10 j
b1110010110101000 v
b1111 b
b111001011010100 ^
b11011010100 M
b11011010100 h
1(
b11101 T
b10011001101 `
b10011001101 Y
b1110010110101000 w
b1101101010000 Q
b1 V
1B
b111111 S
b11100 U
b11011010100 Z
b1010100010010000 3
0:
b10001100 E
b11100 *
b1011010100 <
b1110010110101000 p
b111001011010100 D
b1000110010110101000000000000000 J
b101010 R
b11101 +
b100100001111000100 A
b11001101 =
b1111010011001101 C
b111001011010100 7
b1111010011001101 8
b1 &
1#
#100
0#
#150
b111010000101110 !
b111010000101110 9
b101110 [
b11111010010000 Q
b101110 \
b11111010010000 O
b11111010010000 i
b11111010010000 l
b1111011101111101 F
b11111010010000 m
b11111010010 ]
b11111010010000 n
b11111010010 f
b11111010010 e
b11111010010 a
b11111010010 d
b1110111110100100 G
b1110111110100100 q
b1110111110100100 t
b11111010010 g
b1110111110100100 u
b0 b
b11 P
b11 j
b111010000101110 ^
b1110111110100100 v
b111110100100 o
b10 V
0B
b0 S
b11101 U
b11101001011 Z
b1110111110100100 w
b11111010010 M
b11111010010 h
0(
b11111010010 `
b11111010010 Y
b10111100100101 3
b101011 R
b10001101 E
b11101 *
b1000110111110100100000000000000 J
b1111010010 <
b1110111110100100 p
b111011111010010 D
0;
b11001001010010000110 A
b1101001011 =
b111011101001011 C
b111011111010010 7
b111011101001011 8
b10 &
1#
#200
0#
#250
b110000100010000 !
b110000100010000 9
b0 [
b0 \
b101000100 Q
b0 ]
b1111011000010001 F
b0 a
b0 d
0I
b101000100 n
b101000100 m
b101000100 O
b101000100 i
b101000100 l
b111000 e
b1100001000100000 G
b1100001000100000 q
b1100001000100000 t
b10100010000 o
b1110001000 f
b1100001000100000 u
b110000100010000 ^
b10 P
b10 j
b1110001000 g
b1100001000100000 v
b1101 b
b11011 T
b11 k
1N
b11100010000 `
b11100010000 Y
b1100001000100000 w
b10100010000 M
b10100010000 h
b1 V
1B
b111101 S
b11000 U
b10100010000 Z
b1000011010000 3
b10001000 E
b11000 *
b1000100001000100000000000000000 J
b100010000 <
b1100001000100000 p
b110111100010000 D
b100100 R
b11011 +
b110100000100000000 A
b1100010000 =
b110000100010000 C
b110000100010000 7
b110111100010000 8
b11 &
1#
#300
0#
#350
b110101010101001 !
b110101010101001 9
b11010101001 Q
b11011 e
b11010101001 O
b11010101001 i
b11010101001 l
b1111011010101010 F
b11010101001 m
b11010101001 n
b1101010101010010 G
b1101010101010010 q
b1101010101010010 t
b110111110 f
b11011111010 g
b1101010101010010 u
b0 P
b0 j
b110101010101001 ^
b1101010101010010 v
b11010101001 o
1I
b1110 b
b11010 U
b1 k
0N
b11010101001 Z
b1101010101010010 w
b11010101001 M
b11010101001 h
1(
b111110 S
b11100 T
b11011111010 `
b11011111010 Y
b1001110111111010 3
b10001010 E
b11010 *
b1000101010101010010000000000000 J
b1010101001 <
b1101010101010010 p
b1111001011111010 C
1;
b100111 R
b11100 +
b1111110101100001010 A
b1011111010 =
b110101010101001 D
b110101010101001 7
b1111001011111010 8
b100 &
1#
#400
0#
#450
b0 [
b111010101011001 !
b111010101011001 9
b0 \
b1111011110000001 F
b1011111001000000 O
b1011111001000000 i
b1011111001000000 l
b0 ]
b1111000000111000 G
b1111000000111000 q
b1111000000111000 t
b1011111001000000 m
b10000011 f
b1000 e
b0 a
b0 d
b1111000000111000 u
b1111101111100100 n
0I
b0 V
b100 P
b100 j
b111010101011001 ^
b1111000000111000 v
b1111101111100100 o
b1111 b
b1000001110 g
1B
b11101 U
b10101011001 Z
b1111000000111000 w
b1111101111100100 M
b1111101111100100 h
b1011111001000000 Q
b111111 S
b11110 T
b10000011100 `
b10000011100 Y
b1011000000001001 3
1:
b10001110 E
b11110 *
b11100 <
b1111000000111000 p
b111010101011001 D
b11000111000000111000000000000000 J
0;
b101100 R
b11101 +
b10010110111100 A
b101011001 =
b1111100000011100 C
b1111100000011100 7
b111010101011001 8
b101 &
1#
#500
0#
#550
b10001101 [
b111010010001101 !
b111010010001101 9
b1101110011 \
b1101101110011000 Q
b1111011101001000 F
b10010001101 ]
b1101101110011000 O
b1101101110011000 i
b1101101110011000 l
b10010001101 f
b10010001101 e
b10010001101 a
b10010001101 d
b1101101110011000 m
b10010001101 g
b1110100100011010 G
b1110100100011010 q
b1110100100011010 t
b1101101110011000 n
b1110100100011010 u
b1111011011100110 o
b0 b
b11 P
b11 j
b1110100100011010 v
b1111101101110011 M
b1111101101110011 h
b111010010001101 ^
b10 V
0B
b0 S
b11101 T
b10010001101 `
b10010001101 Y
b1110100100011010 w
b11001111101 Z
b1010110001010111 3
b101011 R
b10001101 E
b11101 *
b11000110100100011010000000000000 J
b10001101 <
b1110100100011010 p
b1111010010001101 C
b10101111011011001 A
b1001111101 =
b111011001111101 D
b1111010010001101 7
b111011001111101 8
b110 &
1#
#600
0#
#650
b1101111110110000 Q
b1111010000001010 !
b1111010000001010 9
b1101111110110000 O
b1101111110110000 i
b1101111110110000 l
b1101111110110000 m
b0 \
b1101111110110000 n
b0 ]
b1111011101000000 F
b0 a
b0 d
b1111011111101100 o
1I
b1011 e
b1110100000010100 G
b1110100000010100 q
b1110100000010100 t
b0 [
b10111110 f
b1110100000010100 u
1B
b11110 T
b1111010000001010 ^
b1011111000 g
b1110100000010100 v
b1111101111110110 M
b1111101111110110 h
b1111 b
b10111110000 `
b10111110000 Y
b1110100000010100 w
0(
b1 V
b111111 S
b11101 U
b10000001010 Z
b11000000000100 3
b11000110100000010100000000000000 J
b1010 <
b1110100000010100 p
b1111100111110000 C
1;
b101100 R
b11110 +
b1001101100000 A
b111110000 =
b1111010000001010 D
b1111010000001010 7
b1111100111110000 8
b111 &
1#
#700
0#
#750
b1100000000011000 Q
b0 [
b111000000010100 !
b111000000010100 9
b1100000000011000 O
b1100000000011000 i
b1100000000011000 l
b1100000000011000 m
b1100000000011000 n
b0 \
b1111011101111111 F
b1111000000000110 o
b0 ]
b1110111111111010 G
b1110111111111010 q
b1110111111111010 t
b11100 U
b11111111 f
b1111 e
b0 a
b0 d
b1111111110 g
b1110111111111010 u
b111000000010100 ^
b1110111111111010 v
b1111100000000011 M
b1111100000000011 h
0I
b0 V
b1111 b
b10000010100 Z
b1110111111111010 w
1(
1B
b111111 S
b11101 T
b11111111101 `
b11111111101 Y
b1010100000010011 3
b11000110111111111010000000000000 J
b1111111101 <
b1110111111111010 p
b111000000010100 D
0;
b101010 R
b11100 +
b100111111000100 A
b10100 =
b1111011111111101 C
b1111011111111101 7
b111000000010100 8
b1000 &
1#
#800
0#
#850
b110011001000101 !
b110011001000101 9
b1001000101 [
b1001000101 \
b1111011001011011 F
1I
b10110111011 ]
b1011011101 o
b1011011101 n
b1011011101 m
b1011011101 O
b1011011101 i
b1011011101 l
b1100101101110110 G
b1100101101110110 q
b1100101101110110 t
b10110111011 g
b10110111011 f
b10110111011 e
b10110111011 a
b10110111011 d
b1100101101110110 u
b1 P
b1 j
b1100101101110110 v
b0 b
b110011001000101 ^
b10110111011 M
b10110111011 h
0(
b10 V
0B
b11001 T
b11 k
1N
b10110111011 `
b10110111011 Y
b1100101101110110 w
b1011011101 Q
b0 S
b11001 U
b11101100100 Z
b110101110111 3
0:
b10001001 E
b11001 *
b110111011 <
b1100101101110110 p
b110011101100100 C
b1000100101101110110000000000000 J
b100011 R
b11001 +
b1011101111000001100 A
b1101100100 =
b110010110111011 D
b110010110111011 7
b110011101100100 8
b1001 &
1#
#900
0#
#950
b1111000010011011 !
b1111000010011011 9
b0 [
b0 \
b1111011110110000 F
b1111100011111111 n
b0 ]
b1000111111110000 m
b1000111111110000 O
b1000111111110000 i
b1000111111110000 l
b1111011000000010 G
b1111011000000010 q
b1111011000000010 t
b1111100011111111 o
b11100 e
b0 a
b0 d
b111000000 f
b1111011000000010 u
0I
b1111000010011011 ^
b100 P
b100 j
b11100000001 g
b1111011000000010 v
b1110 b
1B
b11110 T
b1 k
0N
b11100000001 `
b11100000001 Y
b1111011000000010 w
b1111100011111111 M
b1111100011111111 h
b1000111111110000 Q
b0 V
b111110 S
b11100 U
b10010011011 Z
b10110001110100 3
1:
b10001110 E
b11110 *
b1100000001 <
b1111011000000010 p
b1111000010011011 D
b11000111011000000010000000000000 J
1;
b101011 R
b11100 +
b11101000110011011 A
b10011011 =
b1111101100000001 C
b1111101100000001 7
b1111000010011011 8
b1010 &
1#
#1000
0#
#1050
b1110010101011000 !
b1110010101011000 9
b1100011 e
b1111011101100011 F
b11000111011000 O
b11000111011000 i
b11000111011000 l
b11000111011000 m
b1110110001110110 G
b1110110001110110 q
b1110110001110110 t
b11000111011 f
b11000111011000 n
b1110110001110110 u
b110001110110 o
1I
b11 P
b11 j
b11000111011 g
b1110110001110110 v
b1100 b
b1110010101011000 ^
b11000111011 M
b11000111011 h
1(
b11101 T
b11000111011 `
b11000111011 Y
b1110110001110110 w
b11000111011000 Q
b111100 S
b11001 U
b10101011000 Z
b1001110010111111 3
0:
b10001101 E
b11101 *
b1000111011 <
b1110110001110110 p
b1110010101011000 C
b1000110110001110110000000000000 J
b100111 R
b11001 +
b101111111101001000 A
b101011000 =
b111011000111011 D
b111011000111011 7
b1110010101011000 8
b1011 &
1#
#1100
0#
#1150
b1111001010110111 !
b1111001010110111 9
b110111100000000 Q
b11011 e
b1111011110101111 F
b110111100000000 O
b110111100000000 i
b110111100000000 l
b11011110000 n
b110111100000000 m
b1111010111100000 G
b1111010111100000 q
b1111010111100000 t
b11011110000 o
b110111100 f
b1111010111100000 u
b100 P
b100 j
b11011110000 g
b1111010111100000 v
b1110 b
b1111001010110111 ^
b11110 T
b11011110000 `
b11011110000 Y
b1111010111100000 w
b11011110000 M
b11011110000 h
b111110 S
b11100 U
b11010110111 Z
b1010110111111110 3
b10001110 E
b11110 *
b1000111010111100000000000000000 J
b1011110000 <
b1111010111100000 p
b111101011110000 D
b101011 R
b11100 +
b1111111100110010000 A
b1010110111 =
b1111001010110111 C
b111101011110000 7
b1111001010110111 8
b1100 &
1#
#1200
0#
#1250
b0 [
b1111001111001011 !
b1111001111001011 9
b0 \
b1111011100111100 F
b1110000011010100 O
b1110000011010100 i
b1110000011010100 l
b0 ]
b1110000011010100 m
b1110011110010110 G
b1110011110010110 q
b1110011110010110 t
b11000110 f
b1100 e
b0 a
b0 d
b1110011110010110 u
b1110000011010100 n
0I
b1 V
b10 P
b10 j
b1100011001 g
b1110011110010110 v
b1111100000110101 o
b1111 b
b1111001111001011 ^
1B
b11101 T
b11000110010 `
b11000110010 Y
b1110011110010110 w
b1111100000110101 M
b1111100000110101 h
b1110000011010100 Q
b111111 S
b11100 U
b11111001011 Z
b1010101000010100 3
1:
b10001100 E
b11100 *
b1111001011 <
b1110011110010110 p
b111011000110010 D
b11000110011110010110000000000000 J
0;
b101010 R
b11101 +
b10000101001110100110 A
b1000110010 =
b1111001111001011 C
b1111001111001011 7
b111011000110010 8
b1101 &
1#
#1300
0#
#1350
b110110011010111 !
b110110011010111 9
b1111 e
b11110110 f
b100110101110 O
b100110101110 i
b100110101110 l
b1111011011001101 F
b100110101110 m
b100110101110 n
b1101100110101110 G
b1101100110101110 q
b1101100110101110 t
b1111011001 g
b1101100110101110 u
1I
b100110101110 o
b1 P
b1 j
b110110011010111 ^
b1101100110101110 v
b10011010111 M
b10011010111 h
b11011 U
b10011010111 Z
b1101100110101110 w
b100110101110 Q
1B
b111111 S
b11100 T
b11110110010 `
b11110110010 Y
b1010000011000110 3
0:
b10001011 E
b11011 *
b11010111 <
b1101100110101110 p
b1111001110110010 C
b1000101100110101110000000000000 J
1;
b101000 R
b11100 +
b110001101001111110 A
b1110110010 =
b110110011010111 D
b110110011010111 7
b1111001110110010 8
b1110 &
1#
#1400
0#
#1450
b111010111010000 !
b111010111010000 9
b111010000 [
b11000110000000 Q
b111010000 \
b11000110000000 O
b11000110000000 i
b11000110000000 l
b1111011101100011 F
b11000110000000 m
b11000110000 ]
b11000110000000 n
b1110110001100000 G
b1110110001100000 q
b1110110001100000 t
b110001100000 o
b11000110000 f
b11000110000 e
b11000110000 a
b11000110000 d
b11000110000 g
b1110110001100000 u
b11 P
b11 j
b111010111010000 ^
b1110110001100000 v
1I
b0 b
b10 V
0B
b11101 U
b11001111111 Z
b1110110001100000 w
b11000110000 M
b11000110000 h
0(
b0 S
b11101 T
b11000110000 `
b11000110000 Y
b10110101011101 3
b10001101 E
b11101 *
b1000110110001100000000000000000 J
b1000110000 <
b1110110001100000 p
b111011000110000 D
0;
b101011 R
b11101 +
b1010111010111010000 A
b1001111111 =
b111011001111111 C
b111011000110000 7
b111011001111111 8
b1111 &
1#
#1500
0#
#1550
b1110111010101010 !
b1110111010101010 9
b100011101010000 Q
b0 \
b1111011110000111 F
b100011101010000 O
b100011101010000 i
b100011101010000 l
b0 ]
b10001110101 n
b100011101010000 m
b1111000011101010 G
b1111000011101010 q
b1111000011101010 t
b10001110101 o
b0 [
b100011 e
b0 a
b0 d
b1000111010 f
b1111000011101010 u
b1110111010101010 ^
b100 P
b100 j
b1000111010 g
b1111000011101010 v
b1101 b
b11110 T
b10001110101 `
b10001110101 Y
b1111000011101010 w
b10001110101 M
b10001110101 h
1(
b0 V
1B
b111101 S
b11011 U
b11010101010 Z
b1010100001001101 3
b10001110 E
b11110 *
b1000111000011101010000000000000 J
b1110101 <
b1111000011101010 p
b111100001110101 D
1;
b101010 R
b11011 +
b10011011110110010 A
b1010101010 =
b1110111010101010 C
b111100001110101 7
b1110111010101010 8
b10000 &
1#
#1600
0#
#1650
b0 [
b111000001011000 !
b111000001011000 9
b1000101100000 Q
b0 \
b1111011100000101 F
b1000101100000 O
b1000101100000 i
b1000101100000 l
b10001101 f
b0 ]
b1000101100000 m
b1000110111 g
b1110000010110000 G
b1110000010110000 q
b1110000010110000 t
b1000 e
b0 a
b0 d
b1110000010110000 u
b1000101100000 n
b1 V
b10 P
b10 j
b1110000010110000 v
b10001011000 o
b1111 b
b111000001011000 ^
1B
b11101 T
b10001101110 `
b10001101110 Y
b1110000010110000 w
b10001011000 M
b10001011000 h
b111111 S
b11100 U
b10001011000 Z
b1010100000001001 3
b10001100 E
b11100 *
b1000110000010110000000000000000 J
b1011000 <
b1110000010110000 p
b111000001011000 D
b101010 R
b11101 +
b10010111010000 A
b1101110 =
b1111010001101110 C
b111000001011000 7
b1111010001101110 8
b10001 &
1#
#1700
0#
#1750
b0 [
b110111001111000 !
b110111001111000 9
b1110001110111100 O
b1110001110111100 i
b1110001110111100 l
b0 \
b1111011100110001 F
b1110001110111100 m
b1110001110111100 n
b0 ]
b1110011000100010 G
b1110011000100010 q
b1110011000100010 t
b11011 U
b11100010 f
b1110 e
b0 a
b0 d
b1110001000 g
b1110011000100010 u
0I
b110111001111000 ^
b1110011000100010 v
b1111100011101111 o
b0 V
b1111 b
b11001111000 Z
b1110011000100010 w
b1111100011101111 M
b1111100011101111 h
b1110001110111100 Q
1B
b111111 S
b11100 T
b11100010001 `
b11100010001 Y
b1010000111100100 3
1:
b1100010001 <
b1110011000100010 p
b110111001111000 D
b11000110011000100010000000000000 J
0;
b101000 R
b11011 +
b1111001000111111000 A
b1001111000 =
b1111001100010001 C
b1111001100010001 7
b110111001111000 8
b10010 &
1#
#1800
0#
